{ "compressionlevel":-1,
 "height":12,
 "infinite":false,
 "layers":[
        {
         "data":[1469, 1469, 1469, 1469, 1469, 1469, 1469, 1469, 1469, 1469, 1469, 1469,
            1469, 1221, 1222, 1221, 1222, 1221, 1222, 1221, 1222, 1221, 1222, 1469,
            1469, 1237, 1238, 1237, 1238, 1237, 1238, 1237, 1238, 1237, 1238, 1469,
            1469, 1221, 1222, 1221, 1222, 1221, 1222, 1221, 1222, 1221, 1222, 1469,
            1469, 1237, 1238, 1237, 1238, 1237, 1238, 1237, 1238, 1237, 1238, 1469,
            1469, 1221, 1222, 1221, 1222, 1221, 1222, 1221, 1222, 1221, 1222, 1469,
            1469, 1237, 1238, 1237, 1238, 1237, 1238, 1237, 1238, 1237, 1238, 1469,
            1469, 1221, 1222, 1221, 1222, 1221, 1222, 1221, 1222, 1221, 1222, 1469,
            1469, 1237, 1238, 1237, 1238, 1237, 1238, 1237, 1238, 1237, 1238, 1469,
            1469, 1221, 1222, 1221, 1222, 1221, 1222, 1221, 1222, 1221, 1222, 1469,
            1469, 1237, 1238, 1237, 1238, 1237, 1238, 1237, 1238, 1237, 1238, 1469,
            1469, 1469, 1469, 1469, 1469, 1221, 1222, 1469, 1469, 1469, 1469, 1469],
         "height":12,
         "id":1,
         "name":"ground",
         "opacity":1,
         "type":"tilelayer",
         "visible":true,
         "width":12,
         "x":0,
         "y":0
        }, 
        {
         "data":[0, 0, 0, 0, 0, 0, 0, 0, 0, 3057, 3058, 0,
            0, 3077, 3078, 3435, 3436, 0, 0, 0, 0, 3073, 3074, 0,
            0, 3093, 3094, 3451, 3452, 0, 0, 0, 0, 3089, 3090, 0,
            0, 0, 0, 0, 0, 0, 0, 0, 0, 0, 0, 0,
            0, 2789, 2790, 2791, 2792, 2793, 2794, 0, 0, 0, 0, 0,
            0, 2805, 2806, 2807, 2808, 2809, 2810, 0, 0, 0, 0, 0,
            0, 0, 0, 0, 0, 0, 0, 0, 0, 0, 0, 0,
            0, 2825, 2826, 2889, 2890, 0, 0, 0, 0, 0, 0, 0,
            0, 2841, 2842, 2905, 2906, 0, 0, 0, 0, 0, 0, 0,
            0, 2889, 2890, 0, 0, 0, 0, 0, 0, 0, 0, 0,
            0, 2905, 2906, 0, 0, 0, 0, 0, 0, 0, 0, 0,
            0, 0, 0, 0, 0, 0, 0, 0, 0, 0, 0, 0],
         "height":12,
         "id":2,
         "name":"objects",
         "opacity":1,
         "type":"tilelayer",
         "visible":true,
         "width":12,
         "x":0,
         "y":0
        }, 
        {
         "data":[0, 0, 0, 0, 0, 0, 0, 0, 0, 0, 0, 0,
            0, 0, 0, 0, 0, 0, 0, 0, 0, 0, 0, 0,
            0, 0, 0, 0, 0, 0, 0, 0, 0, 0, 0, 0,
            0, 0, 0, 0, 0, 0, 0, 0, 0, 0, 0, 0,
            0, 3913, 3914, 0, 0, 3915, 3916, 0, 0, 0, 0, 0,
            0, 3929, 3930, 0, 0, 3931, 3932, 0, 0, 0, 0, 0,
            0, 0, 0, 0, 0, 0, 0, 0, 0, 0, 0, 0,
            0, 3919, 3920, 0, 0, 0, 0, 0, 0, 0, 0, 0,
            0, 3935, 3936, 0, 0, 0, 0, 0, 0, 0, 0, 0,
            0, 0, 0, 0, 0, 0, 0, 0, 0, 0, 0, 0,
            0, 0, 0, 0, 0, 0, 0, 0, 0, 0, 0, 0,
            0, 0, 0, 0, 0, 0, 0, 0, 0, 0, 0, 0],
         "height":12,
         "id":4,
         "name":"objectsTop",
         "opacity":1,
         "type":"tilelayer",
         "visible":true,
         "width":12,
         "x":0,
         "y":0
        }, 
        {
         "draworder":"topdown",
         "id":3,
         "name":"collisions",
         "objects":[
                {
                 "height":8.66666666666666,
                 "id":1,
                 "name":"",
                 "rotation":0,
                 "type":"",
                 "visible":true,
                 "width":83.3183107469272,
                 "x":18.5435444899674,
                 "y":67.0636621493854
                }, 
                {
                 "height":5.66666666666667,
                 "id":2,
                 "name":"",
                 "rotation":0,
                 "type":"",
                 "visible":true,
                 "width":25,
                 "x":18.6666666666667,
                 "y":19
                }, 
                {
                 "height":7.66666666666667,
                 "id":4,
                 "name":"",
                 "rotation":0,
                 "type":"",
                 "visible":true,
                 "width":27,
                 "x":18.3333333333333,
                 "y":120.333333333333
                }, 
                {
                 "ellipse":true,
                 "height":8.66666666666667,
                 "id":5,
                 "name":"",
                 "rotation":0,
                 "type":"",
                 "visible":true,
                 "width":8.99999999999999,
                 "x":59,
                 "y":122.666666666667
                }, 
                {
                 "ellipse":true,
                 "height":9.66666666666666,
                 "id":6,
                 "name":"",
                 "rotation":0,
                 "type":"",
                 "visible":true,
                 "width":9.66666666666667,
                 "x":26.3333333333333,
                 "y":153.666666666667
                }, 
                {
                 "height":11.337535455405,
                 "id":7,
                 "name":"",
                 "rotation":0,
                 "type":"",
                 "visible":true,
                 "width":23.7345309381237,
                 "x":150.690093497216,
                 "y":0.496690828868578
                }, 
                {
                 "height":12.6666666666667,
                 "id":8,
                 "name":"",
                 "rotation":0,
                 "type":"",
                 "visible":true,
                 "width":78,
                 "x":113,
                 "y":177.333333333333
                }, 
                {
                 "height":170.333333333333,
                 "id":9,
                 "name":"",
                 "rotation":0,
                 "type":"",
                 "visible":true,
                 "width":11,
                 "x":177.666666666667,
                 "y":4.66666666666667
                }, 
                {
                 "height":13.6306334699023,
                 "id":10,
                 "name":"",
                 "rotation":0,
                 "type":"",
                 "visible":true,
                 "width":140.666666666667,
                 "x":1,
                 "y":0.66666666666667
                }, 
                {
                 "height":181,
                 "id":11,
                 "name":"",
                 "rotation":0,
                 "type":"",
                 "visible":true,
                 "width":10,
                 "x":1.33333333333333,
                 "y":8.66666666666667
                }, 
                {
                 "height":13.6666666666667,
                 "id":12,
                 "name":"",
                 "rotation":0,
                 "type":"",
                 "visible":true,
                 "width":72.6666666666667,
                 "x":4.66666666666667,
                 "y":177
                }, 
                {
                 "height":5.56697132051687,
                 "id":15,
                 "name":"",
                 "rotation":0,
                 "type":"",
                 "visible":true,
                 "width":32.1916167664671,
                 "x":80.1159785691774,
                 "y":192.907658367476
                }],
         "opacity":1,
         "type":"objectgroup",
         "visible":true,
         "x":0,
         "y":0
        }, 
        {
         "draworder":"topdown",
         "id":5,
         "name":"chest",
         "objects":[
                {
                 "height":27.1087299086039,
                 "id":13,
                 "name":"",
                 "rotation":0,
                 "type":"",
                 "visible":true,
                 "width":26.866687677277,
                 "x":50.3447841159786,
                 "y":19.3633785061456
                }],
         "opacity":1,
         "type":"objectgroup",
         "visible":true,
         "x":0,
         "y":0
        }],
 "nextlayerid":6,
 "nextobjectid":16,
 "orientation":"orthogonal",
 "renderorder":"right-down",
 "tiledversion":"git",
 "tileheight":16,
 "tilesets":[
        {
         "columns":16,
         "firstgid":1,
         "image":"tilesets\/pipoya-rpg.png",
         "imageheight":4256,
         "imagewidth":256,
         "margin":0,
         "name":"pipoya-rpg",
         "spacing":0,
         "tilecount":4256,
         "tileheight":16,
         "tilewidth":16
        }],
 "tilewidth":16,
 "type":"map",
 "version":"1.10",
 "width":12
}